{
  "id": "1cfea7aa-fc86-4851-907c-cd7c5c70dc98",
  "paramsKey": "10m_5pct|1772547900342|1772569500342",
  "universeId": "10m_5pct",
  "universeName": "10m/5%",
  "startMs": 1772547900342,
  "endMs": 1772569500342,
  "receivedAtMs": 1772569519608,
  "receivedSymbols": [
    "BTCUSDT",
    "ETHUSDT",
    "SOLUSDT",
    "XRPUSDT",
    "ENSOUSDT",
    "ESPUSDT",
    "DOGEUSDT",
    "POWERUSDT",
    "PIPPINUSDT",
    "HYPEUSDT",
    "1000PEPEUSDT",
    "BCHUSDT",
    "FARTCOINUSDT",
    "SUIUSDT",
    "RIVERUSDT",
    "DOTUSDT",
    "ADAUSDT",
    "SKRUSDT",
    "LINKUSDT",
    "BNBUSDT",
    "AVAXUSDT",
    "ARCUSDT",
    "VIRTUALUSDT",
    "ZECUSDT",
    "LTCUSDT",
    "AAVEUSDT",
    "TAOUSDT",
    "LAUSDT",
    "NEARUSDT",
    "PUMPFUNUSDT",
    "MYXUSDT",
    "WIFUSDT",
    "UNIUSDT",
    "OPUSDT",
    "BERAUSDT",
    "AXLUSDT",
    "ENAUSDT",
    "KITEUSDT",
    "ARBUSDT",
    "AXSUSDT",
    "VVVUSDT",
    "SOMIUSDT",
    "SIRENUSDT",
    "ONDOUSDT",
    "AKEUSDT",
    "STEEMUSDT",
    "HBARUSDT",
    "INJUSDT",
    "SEIUSDT",
    "AZTECUSDT",
    "CRVUSDT",
    "TRUMPUSDT",
    "PENGUUSDT",
    "GALAUSDT",
    "APTUSDT",
    "WLDUSDT",
    "POLUSDT",
    "GPSUSDT",
    "SHIB1000USDT",
    "HOLOUSDT",
    "WLFIUSDT",
    "LITUSDT",
    "ZROUSDT",
    "1000BONKUSDT",
    "XMRUSDT",
    "AGLDUSDT",
    "PIEVERSEUSDT",
    "ETHFIUSDT",
    "XPLUSDT",
    "ATOMUSDT",
    "XLMUSDT",
    "FILUSDT",
    "ICPUSDT"
  ],
  "receivedSymbolsCount": 73,
  "loopsCount": 2
}
