{
  "meta": {
    "id": "1m_1pct",
    "name": "1m/1%",
    "minTurnoverUsd": 1000000,
    "minVolatilityPct": 1,
    "createdAt": 1771945422798,
    "updatedAt": 1771945422798,
    "count": 240
  },
  "symbols": [
    "BTCUSDT",
    "ETHUSDT",
    "SOLUSDT",
    "XRPUSDT",
    "ESPUSDT",
    "PIPPINUSDT",
    "XAUTUSDT",
    "DOGEUSDT",
    "HYPEUSDT",
    "POWERUSDT",
    "SKRUSDT",
    "1000PEPEUSDT",
    "FARTCOINUSDT",
    "ENSOUSDT",
    "BCHUSDT",
    "RIVERUSDT",
    "BNBUSDT",
    "SUIUSDT",
    "ADAUSDT",
    "LINKUSDT",
    "LTCUSDT",
    "AGLDUSDT",
    "AVAXUSDT",
    "ZECUSDT",
    "DOTUSDT",
    "WLFIUSDT",
    "KITEUSDT",
    "AAVEUSDT",
    "ENAUSDT",
    "ASTERUSDT",
    "TAOUSDT",
    "PAXGUSDT",
    "OPUSDT",
    "NEARUSDT",
    "MYXUSDT",
    "STEEMUSDT",
    "AZTECUSDT",
    "SEIUSDT",
    "RAVEUSDT",
    "GPSUSDT",
    "ARBUSDT",
    "PUMPFUNUSDT",
    "AXSUSDT",
    "WIFUSDT",
    "LAUSDT",
    "SENTUSDT",
    "CRVUSDT",
    "VIRTUALUSDT",
    "GALAUSDT",
    "BERAUSDT",
    "HUSDT",
    "ONDOUSDT",
    "SIRENUSDT",
    "UNIUSDT",
    "VVVUSDT",
    "APTUSDT",
    "HBARUSDT",
    "INJUSDT",
    "FOGOUSDT",
    "TRUMPUSDT",
    "TONUSDT",
    "WLDUSDT",
    "ZROUSDT",
    "PENGUUSDT",
    "SHIB1000USDT",
    "XPLUSDT",
    "POLUSDT",
    "TRIAUSDT",
    "XMRUSDT",
    "ORCAUSDT",
    "1000BONKUSDT",
    "XLMUSDT",
    "JTOUSDT",
    "ARCUSDT",
    "MONUSDT",
    "TRXUSDT",
    "MNTUSDT",
    "ICPUSDT",
    "ETCUSDT",
    "FILUSDT",
    "PROMPTUSDT",
    "UMAUSDT",
    "LITUSDT",
    "ATOMUSDT",
    "DYDXUSDT",
    "WHITEWHALEUSDT",
    "SNXUSDT",
    "LPTUSDT",
    "STRKUSDT",
    "RENDERUSDT",
    "IPUSDT",
    "FLOCKUSDT",
    "ZKUSDT",
    "EIGENUSDT",
    "BIOUSDT",
    "MOODENGUSDT",
    "SONICUSDT",
    "LYNUSDT",
    "ELSAUSDT",
    "ZAMAUSDT",
    "SPXUSDT",
    "ETHFIUSDT",
    "FLOWUSDT",
    "LINEAUSDT",
    "BEATUSDT",
    "ORDIUSDT",
    "TIAUSDT",
    "LDOUSDT",
    "DEXEUSDT",
    "SOMIUSDT",
    "HANAUSDT",
    "DASHUSDT",
    "SPACEUSDT",
    "PENDLEUSDT",
    "CLOUSDT",
    "ALGOUSDT",
    "AKEUSDT",
    "AEROUSDT",
    "SANDUSDT",
    "ZILUSDT",
    "JASMYUSDT",
    "0GUSDT",
    "METUSDT",
    "SXTUSDT",
    "JUPUSDT",
    "POPCATUSDT",
    "YGGUSDT",
    "MEUSDT",
    "SPORTFUNUSDT",
    "USELESSUSDT",
    "ENSUSDT",
    "KASUSDT",
    "BANUSDT",
    "XTZUSDT",
    "STABLEUSDT",
    "KAITOUSDT",
    "ZKPUSDT",
    "APEUSDT",
    "MORPHOUSDT",
    "NIGHTUSDT",
    "FIGHTUSDT",
    "PUNDIXUSDT",
    "BREVUSDT",
    "LUNA2USDT",
    "RESOLVUSDT",
    "CAKEUSDT",
    "ALLOUSDT",
    "AWEUSDT",
    "NAORISUSDT",
    "PYTHUSDT",
    "CCUSDT",
    "GASUSDT",
    "SUSDT",
    "BARDUSDT",
    "COWUSDT",
    "WETUSDT",
    "FHEUSDT",
    "TNSRUSDT",
    "AVNTUSDT",
    "HNTUSDT",
    "VANAUSDT",
    "BIRBUSDT",
    "DRIFTUSDT",
    "INITUSDT",
    "JELLYJELLYUSDT",
    "ROSEUSDT",
    "KERNELUSDT",
    "STGUSDT",
    "CROUSDT",
    "GMTUSDT",
    "STORJUSDT",
    "CHZUSDT",
    "PIEVERSEUSDT",
    "CYBERUSDT",
    "ZORAUSDT",
    "RPLUSDT",
    "INUSDT",
    "EULUSDT",
    "PARTIUSDT",
    "ORBSUSDT",
    "MERLUSDT",
    "VETUSDT",
    "OGNUSDT",
    "1000FLOKIUSDT",
    "1000NEIROCTOUSDT",
    "WUSDT",
    "ARUSDT",
    "MOVEUSDT",
    "DUSKUSDT",
    "BOMEUSDT",
    "STXUSDT",
    "WCTUSDT",
    "BTRUSDT",
    "GUNUSDT",
    "NOTUSDT",
    "IOTAUSDT",
    "C98USDT",
    "EGLDUSDT",
    "PLUMEUSDT",
    "JSTUSDT",
    "COTIUSDT",
    "FFUSDT",
    "SKYUSDT",
    "PNUTUSDT",
    "CELOUSDT",
    "SYRUPUSDT",
    "SXPUSDT",
    "NOMUSDT",
    "BELUSDT",
    "BRETTUSDT",
    "GOATUSDT",
    "UBUSDT",
    "ZBTUSDT",
    "MASKUSDT",
    "MUSDT",
    "ONTUSDT",
    "AUCTIONUSDT",
    "ALTUSDT",
    "SAPIENUSDT",
    "IMXUSDT",
    "1000RATSUSDT",
    "MANAUSDT",
    "ZKCUSDT",
    "ROAMUSDT",
    "RUNEUSDT",
    "THETAUSDT",
    "BEAMUSDT",
    "TRUTHUSDT",
    "ZENUSDT",
    "ARKMUSDT",
    "CYSUSDT",
    "APEXUSDT",
    "2ZUSDT",
    "COMPUSDT",
    "1INCHUSDT",
    "INXUSDT",
    "LRCUSDT",
    "GRTUSDT",
    "LIGHTUSDT",
    "LSKUSDT"
  ]
}